asyncio_pool/__init__.py
asyncio_pool/base_pool.py
asyncio_pool/mx_asyncgen.py
asyncio_pool/mx_asynciter.py
asyncio_pool/results.py
asyncio_pool-0.6.0.dist-info/LICENSE.txt
asyncio_pool-0.6.0.dist-info/METADATA
asyncio_pool-0.6.0.dist-info/WHEEL
asyncio_pool-0.6.0.dist-info/top_level.txt
asyncio_pool-0.6.0.dist-info/RECORD
