Metadata-Version: 2.1
Name: asyncio_pool
Version: 0.6.0
Summary: Pool of asyncio coroutines with familiar interface
Home-page: https://github.com/gistart/asyncio-pool
Author: gistart
Author-email: gistart@yandex.ru
License: MIT
Classifier: Programming Language :: Python :: 3
Classifier: Programming Language :: Python :: 3.5
Classifier: Programming Language :: Python :: 3.6
Classifier: Programming Language :: Python :: 3.7
Classifier: License :: OSI Approved :: MIT License
Classifier: Operating System :: OS Independent
Classifier: Framework :: AsyncIO
Requires-Python: >=3.5
License-File: LICENSE.txt
